fbref_scraper_cesc/__init__.py
fbref_scraper_cesc/league_manager.py
fbref_scraper_cesc/player_data.py
fbref_scraper_cesc/team_data.py
fbref_scraper_cesc-0.1.1.dist-info/METADATA
fbref_scraper_cesc-0.1.1.dist-info/WHEEL
fbref_scraper_cesc-0.1.1.dist-info/top_level.txt
fbref_scraper_cesc-0.1.1.dist-info/RECORD
