Metadata-Version: 2.4
Name: fbref_scraper_cesc
Version: 0.1.1
Summary: Una librería para scrapear datos necesarios de la pagina FBREF
Home-page: https://github.com/CescBlanco/proyecto_libreria_Evolve
Author: Cesc Blanco Arnau
Author-email: cesc.blanco98@gmail.com
Classifier: Programming Language :: Python :: 3
Classifier: License :: OSI Approved :: MIT License
Classifier: Operating System :: OS Independent
Requires-Python: >=3.6
Requires-Dist: requests
Requires-Dist: beautifulsoup4
Requires-Dist: pandas
Requires-Dist: numpy
Requires-Dist: lxml
Dynamic: author
Dynamic: author-email
Dynamic: classifier
Dynamic: description
Dynamic: description-content-type
Dynamic: home-page
Dynamic: requires-dist
Dynamic: requires-python
Dynamic: summary
